{
	"assignment": {
		"ATT": [
			"periodic-1"
		],

		"DEF": [
			"periodic-10"
		]
	},

	"configuration":{
		"endTime": "10",
		"dtCost": "0.3",
		"prCost": "0.2",
		"runs per sample": "60",
		"alpha": "0.05",
		"downTime": "7",
        "Probe miss Rate": "0",
        "False probe Rate": "0",
        "Attacker Control Slope": "0",
        "Attacker Control  Shift": "0",
        "Attacker Down Slope": "0",
        "Attacker Down Shift": "0",
        "Attacker Control Weight" : "0",
        "Attacker Down Weight": "0",
        "Defender Control Slope" : "0",
        "Defender Control Shift": "0",
        "Defender Down Slope": "0",
        "Defender Down Shift": "0",
        "Defender Control Weight": "0",
        "Defender Down Weight": "0"
	}


}
